sculblog/__init__.py
sculblog/db.py
sculblog/diego_flavored_markdown.py
sculblog/diego_flavored_markdown_new.py
sculblog/main.py
sculblog/subsection-wrapper.lua
sculblog-0.1.30.dist-info/licenses/LICENSE
sculblog-0.1.30.dist-info/METADATA
sculblog-0.1.30.dist-info/WHEEL
sculblog-0.1.30.dist-info/entry_points.txt
sculblog-0.1.30.dist-info/top_level.txt
sculblog-0.1.30.dist-info/RECORD
