Metadata-Version: 2.4
Name: sculblog
Version: 0.1.30
Summary: Super Cool Utility Lightweight Blog - A minimalist blogging framework
Author: Diego Cabello
Requires-Python: >=3.6
License-File: LICENSE
Requires-Dist: beautifulsoup4
Requires-Dist: pypandoc
Dynamic: author
Dynamic: license-file
Dynamic: requires-dist
Dynamic: requires-python
Dynamic: summary
